schematics/__init__.py
schematics/common.py
schematics/compat.py
schematics/datastructures.py
schematics/deprecated.py
schematics/exceptions.py
schematics/iteration.py
schematics/models.py
schematics/role.py
schematics/schema.py
schematics/transforms.py
schematics/translator.py
schematics/undefined.py
schematics/util.py
schematics/validate.py
schematics/contrib/__init__.py
schematics/contrib/enum_type.py
schematics/contrib/machine.py
schematics/contrib/mongo.py
schematics/extensions/__init__.py
schematics/extensions/model_help_text_mixin.py
schematics/locale/schematics.pot
schematics/locale/de_DE/LC_MESSAGES/schematics.mo
schematics/locale/de_DE/LC_MESSAGES/schematics.po
schematics/locale/pt_BR/LC_MESSAGES/schematics.mo
schematics/locale/pt_BR/LC_MESSAGES/schematics.po
schematics/types/__init__.py
schematics/types/base.py
schematics/types/compound.py
schematics/types/net.py
schematics/types/serializable.py
schematics/types/union.py
schematics-2.1.1.dist-info/LICENSE
schematics-2.1.1.dist-info/METADATA
schematics-2.1.1.dist-info/WHEEL
schematics-2.1.1.dist-info/top_level.txt
schematics-2.1.1.dist-info/RECORD
